Metadata-Version: 1.1
Name: edinet-xbrl
Version: 0.0.2
Summary: A Python Edinet xbrl file parser
Home-page: https://github.com/BuffetCode/edinet_xbrl
Author: https://github.com/shoe116
Author-email: buffett.code.info@gmail.com
License: Apache License 2.0
Keywords: edinet xbrl parser for python
Platform: UNKNOWN
Classifier: Development Status :: 4 - Beta
Classifier: Intended Audience :: Developers
Classifier: Topic :: Software Development :: Build Tools
Classifier: Programming Language :: Python :: 3.3
Classifier: Programming Language :: Python :: 3.4
Classifier: Programming Language :: Python :: 3.5
Classifier: Programming Language :: Python :: 3.6
